{ "height":18,
 "layers":[
        {
         "data":[3, 3, 3, 3, 3, 3, 3, 3, 3, 3, 3, 3, 3, 3, 3, 3, 3, 1, 1, 1, 3, 3, 3, 3, 3, 3, 3, 3, 3, 1, 1, 1, 3, 3, 3, 3, 3, 1, 1, 1, 1, 1, 1, 1, 1, 1, 1, 3, 3, 1, 1, 1, 1, 1, 1, 1, 1, 1, 1, 3, 3, 1, 1, 1, 1, 1, 1, 1, 1, 1, 1, 3, 3, 3, 3, 3, 3, 1, 1, 1, 3, 3, 3, 3, 3, 3, 3, 3, 3, 1, 1, 1, 1, 3, 3, 3, 3, 3, 3, 3, 3, 1, 1, 1, 1, 3, 3, 3, 3, 3, 3, 3, 3, 1, 5, 1, 1, 3, 3, 3, 3, 3, 3, 3, 3, 1, 1, 1, 1, 3, 3, 3, 3, 3, 3, 3, 3, 1, 1, 1, 1, 3, 3, 3, 3, 3, 3, 3, 3, 1, 1, 1, 3, 3, 3, 3, 3, 3, 3, 3, 1, 1, 1, 1, 1, 3, 3, 3, 3, 3, 3, 3, 1, 1, 1, 1, 1, 3, 3, 3, 3, 3, 3, 3, 1, 1, 1, 1, 1, 3, 3, 3, 3, 3, 3, 3, 1, 1, 1, 1, 1, 3, 3, 3, 3, 3, 3, 3, 3, 3, 3, 3, 3, 3, 3, 3],
         "height":18,
         "name":"ground",
         "opacity":1,
         "type":"tilelayer",
         "visible":true,
         "width":12,
         "x":0,
         "y":0
        }, 
        {
         "data":[0, 0, 0, 0, 0, 0, 0, 0, 0, 0, 0, 0, 0, 0, 0, 0, 0, 4, 4, 4, 0, 0, 0, 0, 0, 0, 0, 0, 0, 4, 0, 4, 0, 0, 0, 0, 0, 4, 4, 4, 4, 4, 0, 4, 4, 4, 4, 0, 0, 4, 0, 0, 0, 0, 0, 0, 0, 0, 4, 0, 0, 4, 4, 4, 4, 4, 0, 4, 4, 4, 4, 0, 0, 0, 0, 0, 0, 4, 0, 4, 0, 0, 0, 0, 0, 0, 0, 0, 0, 4, 0, 4, 4, 0, 0, 0, 0, 0, 0, 0, 0, 4, 0, 0, 4, 0, 0, 0, 0, 0, 0, 0, 0, 4, 0, 0, 4, 0, 0, 0, 0, 0, 0, 0, 0, 4, 0, 0, 4, 0, 0, 0, 0, 0, 0, 0, 0, 4, 0, 4, 4, 0, 0, 0, 0, 0, 0, 0, 0, 4, 0, 4, 0, 0, 0, 0, 0, 0, 0, 0, 4, 4, 0, 4, 4, 0, 0, 0, 0, 0, 0, 0, 4, 0, 0, 0, 4, 0, 0, 0, 0, 0, 0, 0, 4, 0, 0, 0, 4, 0, 0, 0, 0, 0, 0, 0, 4, 4, 4, 4, 4, 0, 0, 0, 0, 0, 0, 0, 0, 0, 0, 0, 0, 0, 0, 0],
         "height":18,
         "name":"walls",
         "opacity":1,
         "properties":
            {
             "collide":"true"
            },
         "type":"tilelayer",
         "visible":true,
         "width":12,
         "x":0,
         "y":0
        }, 
        {
         "height":18,
         "name":"special",
         "objects":[
                {
                 "gid":5,
                 "height":0,
                 "name":"trap0",
                 "properties":
                    {

                    },
                 "type":"event",
                 "visible":true,
                 "width":0,
                 "x":720,
                 "y":1200
                }, 
                {
                 "gid":8,
                 "height":0,
                 "name":"start",
                 "properties":
                    {
                     "e":"hall0",
                     "long":"Gregory is in a closet. This is not home.",
                     "short":"a closet"
                    },
                 "type":"zone",
                 "visible":true,
                 "width":0,
                 "x":240,
                 "y":600
                }, 
                {
                 "gid":8,
                 "height":0,
                 "name":"hall0",
                 "properties":
                    {
                     "long":"Gregory is in a narrow hall with a door on every on wall. Too many choices.",
                     "n":"finish",
                     "s":"trap0n",
                     "short":"a narrow hallway",
                     "w":"start"
                    },
                 "type":"zone",
                 "visible":true,
                 "width":0,
                 "x":720,
                 "y":600
                }, 
                {
                 "gid":8,
                 "height":0,
                 "name":"trap0n",
                 "properties":
                    {
                     "e":"trap0ne",
                     "long":"Gregory is just north of an oddly colored floor tile that seems to be... bubbling?!? He can walk over it or around it.",
                     "n":"hall0",
                     "s":"trap0s",
                     "short":"a hall with a mysterious tile"
                    },
                 "type":"zone",
                 "visible":true,
                 "width":0,
                 "x":720,
                 "y":1080
                }, 
                {
                 "gid":8,
                 "height":0,
                 "name":"trap0ne",
                 "properties":
                    {
                     "long":"Gregory is avoiding the mysterious tile.",
                     "short":"a way around"
                    },
                 "type":"zone",
                 "visible":true,
                 "width":0,
                 "x":840,
                 "y":1080
                }, 
                {
                 "gid":8,
                 "height":0,
                 "name":"trap0se",
                 "properties":
                    {
                     "long":"Gregory is avoiding the mysterious tile.",
                     "n":"trap0ne",
                     "short":"a way around",
                     "w":"trap0s"
                    },
                 "type":"zone",
                 "visible":true,
                 "width":0,
                 "x":840,
                 "y":1320
                }, 
                {
                 "gid":8,
                 "height":0,
                 "name":"trap0s",
                 "properties":
                    {
                     "e":"trap0se",
                     "long":"Gregory is just south of an oddly colored floor tile that seems to be... bubbling?!? He can walk over it or around it.",
                     "n":"trap0n",
                     "s":"monocle",
                     "short":"a hall with a mysterious tile"
                    },
                 "type":"zone",
                 "visible":true,
                 "width":0,
                 "x":720,
                 "y":1320
                }, 
                {
                 "gid":8,
                 "height":0,
                 "name":"monocle",
                 "properties":
                    {
                     "long":"This room looks like it used to be an old study. There could be valuable things in here.",
                     "n":"trap0s",
                     "short":"an old study"
                    },
                 "type":"zone",
                 "visible":true,
                 "width":0,
                 "x":720,
                 "y":1920
                }, 
                {
                 "gid":8,
                 "height":0,
                 "name":"finish",
                 "properties":
                    {
                     "long":"This looks like the way home!",
                     "s":"hall0",
                     "short":"the way home"
                    },
                 "type":"zone",
                 "visible":true,
                 "width":0,
                 "x":720,
                 "y":360
                }, 
                {
                 "gid":5,
                 "height":0,
                 "name":"finish",
                 "properties":
                    {

                    },
                 "type":"event",
                 "visible":true,
                 "width":0,
                 "x":720,
                 "y":360
                }, 
                {
                 "gid":8,
                 "height":0,
                 "name":"keyboard_keys",
                 "properties":
                    {
                     "long":"Oh great! -_- Gregory has found his way into another closet... but what's this?",
                     "short":"another closet",
                     "w":"hall0"
                    },
                 "type":"zone",
                 "visible":true,
                 "width":0,
                 "x":1080,
                 "y":600
                }],
         "opacity":0.569999992847443,
         "type":"objectgroup",
         "visible":true,
         "width":12,
         "x":0,
         "y":0
        }, 
        {
         "height":18,
         "name":"items",
         "objects":[
                {
                 "gid":9,
                 "height":0,
                 "name":"monocle",
                 "properties":
                    {

                    },
                 "type":"item",
                 "visible":true,
                 "width":0,
                 "x":720,
                 "y":1920
                }, 
                {
                 "gid":10,
                 "height":0,
                 "name":"key0",
                 "properties":
                    {

                    },
                 "type":"key",
                 "visible":true,
                 "width":0,
                 "x":480,
                 "y":600
                }, 
                {
                 "gid":12,
                 "height":0,
                 "name":"keyboard_keys",
                 "properties":
                    {

                    },
                 "type":"item",
                 "visible":true,
                 "width":0,
                 "x":1080,
                 "y":600
                }, 
                {
                 "gid":10,
                 "height":0,
                 "name":"key1",
                 "properties":
                    {

                    },
                 "type":"key",
                 "visible":true,
                 "width":0,
                 "x":960,
                 "y":600
                }, 
                {
                 "gid":7,
                 "height":0,
                 "name":"start",
                 "properties":
                    {

                    },
                 "type":"door",
                 "visible":true,
                 "width":0,
                 "x":360,
                 "y":600
                }, 
                {
                 "gid":7,
                 "height":0,
                 "name":"hall0e",
                 "properties":
                    {

                    },
                 "type":"door",
                 "visible":true,
                 "width":0,
                 "x":840,
                 "y":600
                }, 
                {
                 "gid":7,
                 "height":0,
                 "name":"hall0n",
                 "properties":
                    {

                    },
                 "type":"door",
                 "visible":true,
                 "width":0,
                 "x":720,
                 "y":480
                }, 
                {
                 "gid":7,
                 "height":0,
                 "name":"hall0s",
                 "properties":
                    {

                    },
                 "type":"door",
                 "visible":true,
                 "width":0,
                 "x":720,
                 "y":720
                }],
         "opacity":0.600000023841858,
         "type":"objectgroup",
         "visible":true,
         "width":12,
         "x":0,
         "y":0
        }],
 "orientation":"orthogonal",
 "properties":
    {

    },
 "tileheight":120,
 "tilesets":[
        {
         "firstgid":1,
         "image":"..\/tilesets\/map.png",
         "imageheight":360,
         "imagewidth":480,
         "margin":0,
         "name":"map_tiles",
         "properties":
            {

            },
         "spacing":0,
         "tileheight":120,
         "tilewidth":120
        }],
 "tilewidth":120,
 "version":1,
 "width":12
}